markets_analytics_databricks/__init__.py
markets_analytics_databricks/gsheet_helper.py
markets_analytics_databricks/redshift_connector.py
markets_analytics_databricks/trino_connector.py
markets_analytics_databricks-0.0.12.dist-info/METADATA
markets_analytics_databricks-0.0.12.dist-info/WHEEL
markets_analytics_databricks-0.0.12.dist-info/licenses/LICENSE
markets_analytics_databricks-0.0.12.dist-info/RECORD
