Metadata-Version: 2.4
Name: markets_analytics_databricks
Version: 0.0.12
Summary: A utility package to handle data analytics
Project-URL: Homepage, https://github.bus.zalan.do/lounge-sales-markets/databricks_package
Project-URL: Issues, https://github.bus.zalan.do/lounge-sales-markets/databricks_package/issues
Author-email: Danyal Imran <danyal.imran@zalando.de>
License-File: LICENSE
Classifier: License :: OSI Approved :: MIT License
Classifier: Operating System :: OS Independent
Classifier: Programming Language :: Python :: 3
Requires-Python: >=3.8
